AUTHORS
LICENSE
MANIFEST.in
README.md
setup.cfg
setup.py
golangenv/__init__.py
golangenv/_version.py
golangenv/app.py
golangenv.egg-info/PKG-INFO
golangenv.egg-info/SOURCES.txt
golangenv.egg-info/dependency_links.txt
golangenv.egg-info/entry_points.txt
golangenv.egg-info/top_level.txt