Metadata-Version: 1.1
Name: golangenv
Version: 0.1
Summary: manage golang in your virtualenv
Home-page: http://github.com/twang817/golangenv
Author: Tommy Wang
Author-email: twang@august8.net
License: MIT
Download-URL: https://github.com/twang817/golangenv/tarball/0.1
Keywords: golang virtualenv
Platform: any
Classifier: Development Status :: 4 - Beta
Classifier: Intended Audience :: Developers
